ham2spec-0.6.2.dist-info/METADATA
ham2spec-0.6.2.dist-info/WHEEL
ham2spec/__init__.py
ham2spec/ham2spec.cpython-38-darwin.so
ham2spec-0.6.2.dist-info/RECORD
