Metadata-Version: 2.1
Name: ham2spec
Version: 0.6.2
Classifier: Programming Language :: Rust
Classifier: Programming Language :: Python :: Implementation :: CPython
Classifier: Programming Language :: Python :: Implementation :: PyPy
Summary: A Python extension for computing spectra from Hamiltonians
Author-email: Zach Mitchell <zmitchell@fastmail.com>
Requires-Python: >=3.6
